rifft/__init__.py
rifft/_internal.abi3.so
rifft/bench.py
rifft/bridge.py
rifft/canonicalize.py
rifft/dlpack_utils.py
rifft/helpers.py
rifft/runtime.py
rifft-1.1.2.dist-info/METADATA
rifft-1.1.2.dist-info/WHEEL
rifft-1.1.2.dist-info/licenses/LICENSE-APACHE
rifft-1.1.2.dist-info/licenses/LICENSE-MIT
rifft-1.1.2.dist-info/RECORD
