Metadata-Version: 2.4
Name: rifft
Version: 1.1.2
Classifier: Development Status :: 3 - Alpha
Classifier: Intended Audience :: Developers
Classifier: License :: OSI Approved :: Apache Software License
Classifier: Programming Language :: Python
Classifier: Programming Language :: Python :: 3
Classifier: Programming Language :: Python :: 3 :: Only
Classifier: Programming Language :: Python :: 3.9
Classifier: Programming Language :: Python :: 3.10
Classifier: Programming Language :: Python :: 3.11
Classifier: Programming Language :: Python :: 3.12
Classifier: Programming Language :: Rust
Classifier: Topic :: Scientific/Engineering
Classifier: Topic :: Software Development :: Libraries
Requires-Dist: numpy>=1.24
Requires-Dist: torch>=2.1 ; extra == 'bench'
Requires-Dist: pytest>=7 ; extra == 'test'
Requires-Dist: torch>=2.1 ; extra == 'test'
Requires-Dist: torch>=2.1 ; extra == 'torch'
Provides-Extra: bench
Provides-Extra: test
Provides-Extra: torch
License-File: LICENSE-APACHE
License-File: LICENSE-MIT
Summary: RIFFT zero-copy FFT bindings
Keywords: fft,dlpack,torch,rayon,simd
Home-Page: https://github.com/benschneider/rifft
Author: Ben Schneider
License: Apache-2.0 OR MIT
Requires-Python: >=3.9
Project-URL: Bug Tracker, https://github.com/benschneider/rifft/issues
Project-URL: Homepage, https://github.com/benschneider/rifft
Project-URL: Source, https://github.com/benschneider/rifft
